bloc/MarkovChain.py
bloc/__init__.py
bloc/analyzer.py
bloc/classifiers.py
bloc/eval_support.py
bloc/generator.py
bloc/subcommands.py
bloc/symbols.json
bloc/tweet_generators.py
bloc/util.py
bloc/v2_support.py
bloc/version.py
twitterbloc-1.2.1.data/scripts/bloc
twitterbloc-1.2.1.dist-info/LICENSE
twitterbloc-1.2.1.dist-info/METADATA
twitterbloc-1.2.1.dist-info/WHEEL
twitterbloc-1.2.1.dist-info/top_level.txt
twitterbloc-1.2.1.dist-info/RECORD
