Metadata-Version: 2.1
Name: twitterbloc
Version: 1.2.1
Summary: Behavioral Languages for Online Characterization (BLOC): Languages for Modeling Social Media Account Behaviors.
Home-page: https://github.com/anwala/bloc
Author: Alexander C. Nwala
Author-email: acnwala@wm.edu
License: MIT
Platform: UNKNOWN
Classifier: Programming Language :: Python :: 3
Classifier: License :: OSI Approved :: MIT License
Classifier: Operating System :: OS Independent
Requires-Dist: numpy
Requires-Dist: osometweet
Requires-Dist: requests-oauthlib
Requires-Dist: scipy
Requires-Dist: scikit-learn
Requires-Dist: textblob
Requires-Dist: urllib3 (<2.0)
